{
  "fontFamily": "sans-serif",
  "primaryColor": "#007bff",
  "secondaryColor": "#6c757d",
  "headerBackColor": "#f8f9fa",
  "headerForeColor": "#343a40",
  "subHeaderBackColor": "#e9ecef",
  "subHeaderForeColor": "#495057",
  "primaryButtonBackColor": "#007bff",
  "primaryButtonForeColor": "#ffffff",
  "primaryButtonHoverBackColor": "#0056b3",
  "primaryButtonHoverForeColor": "#ffffff",
  "secondaryButtonBackColor": "#0056b3",
  "secondaryButtonForeColor": "#ffffff",
  "secondaryButtonHoverBackColor": "#5a6268",
  "secondaryButtonHoverForeColor": "#ffffff",
  "sideBarBackColor": "#343A40",
  "sideBarForeColor": "#ffffff",
  "sideBarActiveBackColor": "#495057",
  "sideBarActiveForeColor": "#ffffff",
  "sideBarItemHoverBackColor": "#495057",
  "sideBarItemHoverForeColor": "#ffffff",
  "sideBarItemSeparatorColor": "#6c757d",
  "sideBarSubItemActiveBackColor": "#1580d1",
  "sideBarSubItemActiveForeColor": "#ffffff",
  "sideBarSubItemHoverBackColor": "#de6455",
  "sideBarSubItemHoverForeColor": "#ffffff",
  "gridHeaderBackColor": "#ffffff",
  "gridHeaderForeColor": "#343a40",
  "gridheaderHoverBackColor": "#ffffff",
  "gridheaderHoverForeColor": "#495057",
  "gridRowBackColor": "#ffffff",
  "gridRowForeColor": "#343a40",
  "gridRowHoverBackColor": "#f8f9fa",
  "gridRowAltBackColor": "#e9ecef",
  "gridRowAltForeColor": "#495057",
  "cardBackColor": "#ffffff",
  "cardForeColor": "#343a40",
  "cardHoverBackColor": "#ffffff",
  "cardHoverForeColor": "#ffffff",
  "logoImageUrl": "assets/one_user.png",
  "logoImageAltText": "Application Logo",
  "mobileLogoImageUrl": "assets/logo.png",
  "mobileLogoImageAltText": "Mobile Application Logo"
}